djtools/__init__.py
djtools/contactrequests/__init__.py
djtools/contactrequests/admin.py
djtools/contactrequests/apps.py
djtools/contactrequests/forms.py
djtools/contactrequests/models.py
djtools/contactrequests/services.py
djtools/contactrequests/views.py
djtools/contactrequests/locale/en/LC_MESSAGES/django.mo
djtools/contactrequests/locale/en/LC_MESSAGES/django.po
djtools/contactrequests/locale/es/LC_MESSAGES/django.mo
djtools/contactrequests/locale/es/LC_MESSAGES/django.po
djtools/contactrequests/migrations/0001_initial.py
djtools/contactrequests/migrations/__init__.py
djtools/contactrequests/templates/djtools/contactrequests/contactrequest_email.txt
djtools/contactrequests/templates/djtools/contactrequests/contactrequest_form.html
django_tools_contact_requests-1.0.2.dist-info/LICENSE
django_tools_contact_requests-1.0.2.dist-info/METADATA
django_tools_contact_requests-1.0.2.dist-info/WHEEL
django_tools_contact_requests-1.0.2.dist-info/top_level.txt
django_tools_contact_requests-1.0.2.dist-info/RECORD
